ger_senhas/__init__.py
ger_senhas/gerador_de_senhas.py
ger_senhas-0.0.1.dist-info/METADATA
ger_senhas-0.0.1.dist-info/WHEEL
ger_senhas-0.0.1.dist-info/top_level.txt
ger_senhas-0.0.1.dist-info/RECORD
