Metadata-Version: 2.1
Name: ger-senhas
Version: 0.0.1
Summary: Programa gerador de senhas
Home-page: https://github.com/fellipemarlus/gerador_senhas
Author: Fellipe Marlus
Author-email: fellipemarlus@hotmail.com
License: UNKNOWN
Platform: UNKNOWN
Requires-Python: >=3.8
Requires-Dist: setuptools
